crashkit/__init__.py
crashkit/db.py
crashkit/home.py
crashkit/schema.sql
crashkit/settings.py
crashkit/slug.py
crashkit/token.py
crashkit/api/command.py
crashkit/api/instrument.py
crashkit/api/sequence.py
crashkit/api/state.py
crashkit/static/favicon.svg
crashkit/static/material-symbols-outlined.woff2
crashkit/static/open-sans-bold.woff2
crashkit/static/open-sans-medium.woff2
crashkit/static/open-sans-regular.woff2
crashkit/static/site.css
crashkit/templates/404_not_found.html
crashkit/templates/base.htm
crashkit/templates/create_command.html
crashkit/templates/create_instrument.html
crashkit/templates/create_sequence.html
crashkit/templates/create_state.html
crashkit/templates/home.html
crashkit/templates/settings.html
crashkit/templates/update_command.html
crashkit/templates/update_instrument.html
crashkit/templates/update_sequence.html
crashkit/templates/update_state.html
crashkit-0.0.1.dist-info/LICENSE
crashkit-0.0.1.dist-info/METADATA
crashkit-0.0.1.dist-info/WHEEL
crashkit-0.0.1.dist-info/top_level.txt
crashkit-0.0.1.dist-info/RECORD
