Metadata-Version: 2.1
Name: crashkit
Version: 0.0.1
Summary: Instrumentation hardware orchestration platform.
License: BSD 3-Clause License
Project-URL: homepage, https://github.com/mcpcpc/crashkit
Project-URL: repository, https://github.com/mcpcpc/crashkit
Keywords: instrumentation,scpi
Requires-Python: >=3.11
License-File: LICENSE
Requires-Dist: pyjwt
Requires-Dist: quart
Requires-Dist: uscpi >=0.3.0
Provides-Extra: dev
Requires-Dist: black ; extra == 'dev'
Requires-Dist: coverage ; extra == 'dev'
Provides-Extra: prod
Requires-Dist: uvicorn ; extra == 'prod'
